{
  "annotations": {
    "list": [
      {
        "builtIn": 1,
        "datasource": "-- Grafana --",
        "enable": true,
        "hide": true,
        "iconColor": "rgba(0, 211, 255, 1)",
        "name": "Annotations & Alerts",
        "target": {
          "limit": 100,
          "matchAny": false,
          "tags": [],
          "type": "dashboard"
        },
        "type": "dashboard"
      }
    ]
  },
  "editable": true,
  "fiscalYearStartMonth": 0,
  "graphTooltip": 0,
  "id": 16,
  "iteration": 1649102638317,
  "links": [
    {
      "asDropdown": false,
      "icon": "external link",
      "includeVars": true,
      "keepTime": false,
      "tags": [
        "TRMMClientOverview"
      ],
      "targetBlank": false,
      "title": "T-RMM Client Overview",
      "tooltip": "",
      "type": "dashboards",
      "url": ""
    },
    {
      "asDropdown": false,
      "icon": "external link",
      "includeVars": true,
      "keepTime": false,
      "tags": [
        "TRMMClientMap"
      ],
      "targetBlank": false,
      "title": "T-RMM Client Map",
      "tooltip": "",
      "type": "dashboards",
      "url": ""
    }
  ],
  "liveNow": false,
  "panels": [
    {
      "collapsed": false,
      "gridPos": {
        "h": 1,
        "w": 24,
        "x": 0,
        "y": 0
      },
      "id": 49,
      "panels": [],
      "title": "Information of the selected agent",
      "type": "row"
    },
    {
      "datasource": {
        "type": "postgres",
        "uid": "${Tactical}"
      },
      "fieldConfig": {
        "defaults": {
          "color": {
            "mode": "thresholds"
          },
          "mappings": [],
          "thresholds": {
            "mode": "absolute",
            "steps": [
              {
                "color": "green",
                "value": null
              },
              {
                "color": "red",
                "value": 80
              }
            ]
          }
        },
        "overrides": []
      },
      "gridPos": {
        "h": 1,
        "w": 24,
        "x": 0,
        "y": 1
      },
      "id": 57,
      "options": {
        "colorMode": "none",
        "graphMode": "none",
        "justifyMode": "auto",
        "orientation": "auto",
        "reduceOptions": {
          "calcs": [
            "lastNotNull"
          ],
          "fields": "/.*/",
          "values": true
        },
        "text": {
          "valueSize": 18
        },
        "textMode": "value"
      },
      "pluginVersion": "8.4.5",
      "targets": [
        {
          "datasource": {
            "type": "postgres",
            "uid": "${Tactical}"
          },
          "format": "table",
          "group": [],
          "metricColumn": "none",
          "rawQuery": true,
          "rawSql": "select \n  concat('Site: ',clients_site.name,' / HostName: ', agents_agent.hostname,' ',agents_agent.DESCRIPTION)\nfrom \n  agents_agent\n  LEFT OUTER JOIN clients_site on agents_agent.site_id = clients_site.id\n  where \n    agents_agent.hostname = $Agents_HostName",
          "refId": "A",
          "select": [
            [
              {
                "params": [
                  "boot_time"
                ],
                "type": "column"
              }
            ]
          ],
          "table": "agents_agent",
          "timeColumn": "last_seen",
          "timeColumnType": "timestamp",
          "where": [
            {
              "name": "$__timeFilter",
              "params": [],
              "type": "macro"
            }
          ]
        }
      ],
      "type": "stat"
    },
    {
      "datasource": {
        "type": "postgres",
        "uid": "${Tactical}"
      },
      "fieldConfig": {
        "defaults": {
          "color": {
            "mode": "thresholds"
          },
          "mappings": [
            {
              "options": {
                "Connected": {
                  "color": "dark-green",
                  "index": 1
                },
                "No Connected": {
                  "color": "dark-red",
                  "index": 0
                }
              },
              "type": "value"
            },
            {
              "options": {
                "match": "null",
                "result": {
                  "color": "transparent",
                  "index": 2
                }
              },
              "type": "special"
            }
          ],
          "thresholds": {
            "mode": "absolute",
            "steps": [
              {
                "color": "transparent",
                "value": null
              },
              {
                "color": "red",
                "value": 80
              }
            ]
          }
        },
        "overrides": []
      },
      "gridPos": {
        "h": 2,
        "w": 1,
        "x": 0,
        "y": 2
      },
      "id": 53,
      "options": {
        "colorMode": "background",
        "graphMode": "area",
        "justifyMode": "auto",
        "orientation": "auto",
        "reduceOptions": {
          "calcs": [],
          "fields": "/.*/",
          "values": false
        },
        "text": {},
        "textMode": "value"
      },
      "pluginVersion": "8.4.5",
      "targets": [
        {
          "datasource": {
            "type": "postgres",
            "uid": "${Tactical}"
          },
          "format": "table",
          "group": [],
          "metricColumn": "none",
          "rawQuery": true,
          "rawSql": "select   \r\nCASE\r\n  WHEN (count(*) = 1) THEN 'Connected'\r\n  WHEN (count(*) = 0) THEN 'No Connected'\r\n  ELSE ''\r\n END AS modifiedpvc\r\n  \r\n from \r\n  agents_agent\r\n where \r\n   agents_agent.hostname = $Agents_HostName  and\r\n   last_seen > NOW()- interval '1 hours'\r\n ",
          "refId": "A",
          "select": [
            [
              {
                "params": [
                  "boot_time"
                ],
                "type": "column"
              }
            ]
          ],
          "table": "agents_agent",
          "timeColumn": "last_seen",
          "timeColumnType": "timestamp",
          "where": [
            {
              "name": "$__timeFilter",
              "params": [],
              "type": "macro"
            }
          ]
        }
      ],
      "type": "stat"
    },
    {
      "datasource": {
        "type": "postgres",
        "uid": "${Tactical}"
      },
      "fieldConfig": {
        "defaults": {
          "color": {
            "mode": "thresholds"
          },
          "mappings": [],
          "thresholds": {
            "mode": "absolute",
            "steps": [
              {
                "color": "text",
                "value": null
              },
              {
                "color": "red",
                "value": 80
              }
            ]
          }
        },
        "overrides": []
      },
      "gridPos": {
        "h": 2,
        "w": 4,
        "x": 1,
        "y": 2
      },
      "id": 63,
      "options": {
        "colorMode": "value",
        "graphMode": "area",
        "justifyMode": "auto",
        "orientation": "auto",
        "reduceOptions": {
          "calcs": [
            "lastNotNull"
          ],
          "fields": "/^concat$/",
          "values": false
        },
        "text": {},
        "textMode": "auto"
      },
      "pluginVersion": "8.4.5",
      "targets": [
        {
          "datasource": {
            "type": "postgres",
            "uid": "${Tactical}"
          },
          "format": "table",
          "group": [],
          "metricColumn": "none",
          "rawQuery": true,
          "rawSql": "SELECT \r\n  concat(\r\n          to_char(now() - to_timestamp(boot_time) ,'DD' ),' Days ', \r\n          to_char(now() - to_timestamp(boot_time),'HH24' ), ' Hours',\r\n          to_char(now() - to_timestamp(boot_time),'MI' ), ' Minutes',\r\n          to_char(now() - to_timestamp(boot_time),'SS' ), ' Secondes'\r\n        )\r\nFrom \r\n  agents_agent\r\nWhere\r\n  agents_agent.hostname = $Agents_HostName",
          "refId": "A",
          "select": [
            [
              {
                "params": [
                  "boot_time"
                ],
                "type": "column"
              }
            ]
          ],
          "table": "agents_agent",
          "timeColumn": "last_seen",
          "timeColumnType": "timestamp",
          "where": [
            {
              "name": "$__timeFilter",
              "params": [],
              "type": "macro"
            }
          ]
        }
      ],
      "title": "Online since",
      "type": "stat"
    },
    {
      "datasource": {
        "type": "postgres",
        "uid": "${Tactical}"
      },
      "description": "Track CPU consumption for the selected agent.",
      "fieldConfig": {
        "defaults": {
          "color": {
            "mode": "palette-classic"
          },
          "custom": {
            "axisLabel": "",
            "axisPlacement": "auto",
            "barAlignment": 0,
            "drawStyle": "line",
            "fillOpacity": 0,
            "gradientMode": "none",
            "hideFrom": {
              "legend": false,
              "tooltip": false,
              "viz": false
            },
            "lineInterpolation": "smooth",
            "lineStyle": {
              "fill": "solid"
            },
            "lineWidth": 1,
            "pointSize": 5,
            "scaleDistribution": {
              "log": 10,
              "type": "log"
            },
            "showPoints": "always",
            "spanNulls": false,
            "stacking": {
              "group": "A",
              "mode": "normal"
            },
            "thresholdsStyle": {
              "mode": "line+area"
            }
          },
          "mappings": [],
          "thresholds": {
            "mode": "percentage",
            "steps": [
              {
                "color": "green",
                "value": null
              },
              {
                "color": "#EAB839",
                "value": 70
              },
              {
                "color": "dark-red",
                "value": 90
              }
            ]
          }
        },
        "overrides": []
      },
      "gridPos": {
        "h": 11,
        "w": 7,
        "x": 5,
        "y": 2
      },
      "id": 28,
      "options": {
        "legend": {
          "calcs": [],
          "displayMode": "hidden",
          "placement": "bottom"
        },
        "tooltip": {
          "mode": "multi",
          "sort": "none"
        }
      },
      "pluginVersion": "8.0.3",
      "targets": [
        {
          "datasource": {
            "type": "postgres",
            "uid": "${Tactical}"
          },
          "format": "time_series",
          "group": [],
          "metricColumn": "none",
          "rawQuery": true,
          "rawSql": "SELECT \r\n  x AS \"time\",\r\n  y as \"CPU Load\"\r\n  FROM checks_checkhistory\r\n  \r\n  WHERE x BETWEEN $__timeFrom() and $__timeTo() --'2021-07-01T13:54:25.526Z' AND '2100-07-02T19:54:25.526Z'\r\n  AND check_id IN (SELECT id FROM checks_check WHERE agent_id=(SELECT id FROM agents_agent where agents_agent.hostname = $Agents_HostName) AND check_type='cpuload')\r\n  ORDER BY x",
          "refId": "A",
          "select": [
            [
              {
                "params": [
                  "boot_time"
                ],
                "type": "column"
              }
            ]
          ],
          "table": "agents_agent",
          "timeColumn": "last_seen",
          "timeColumnType": "timestamp",
          "where": [
            {
              "name": "$__timeFilter",
              "params": [],
              "type": "macro"
            }
          ]
        }
      ],
      "title": "CPU Load",
      "type": "timeseries"
    },
    {
      "datasource": {
        "type": "postgres",
        "uid": "${Tactical}"
      },
      "description": "Track memory consumption for the selected agent.",
      "fieldConfig": {
        "defaults": {
          "color": {
            "mode": "palette-classic"
          },
          "custom": {
            "axisLabel": "",
            "axisPlacement": "auto",
            "barAlignment": 0,
            "drawStyle": "line",
            "fillOpacity": 0,
            "gradientMode": "hue",
            "hideFrom": {
              "legend": false,
              "tooltip": false,
              "viz": false
            },
            "lineInterpolation": "smooth",
            "lineWidth": 1,
            "pointSize": 5,
            "scaleDistribution": {
              "log": 10,
              "type": "log"
            },
            "showPoints": "auto",
            "spanNulls": false,
            "stacking": {
              "group": "A",
              "mode": "none"
            },
            "thresholdsStyle": {
              "mode": "line+area"
            }
          },
          "mappings": [],
          "thresholds": {
            "mode": "percentage",
            "steps": [
              {
                "color": "green",
                "value": null
              },
              {
                "color": "dark-orange",
                "value": 70
              },
              {
                "color": "dark-red",
                "value": 85
              }
            ]
          }
        },
        "overrides": []
      },
      "gridPos": {
        "h": 11,
        "w": 6,
        "x": 12,
        "y": 2
      },
      "id": 29,
      "options": {
        "legend": {
          "calcs": [],
          "displayMode": "hidden",
          "placement": "bottom"
        },
        "tooltip": {
          "mode": "multi",
          "sort": "none"
        }
      },
      "pluginVersion": "8.0.3",
      "targets": [
        {
          "datasource": {
            "type": "postgres",
            "uid": "${Tactical}"
          },
          "format": "time_series",
          "group": [],
          "metricColumn": "none",
          "rawQuery": true,
          "rawSql": "SELECT \r\n  x AS \"time\",\r\n  y as \"Memory Usage\"\r\nFROM \r\n  checks_checkhistory\r\nWHERE \r\n  x BETWEEN $__timeFrom() AND $__timeTo() AND \r\n  check_id IN (SELECT id FROM checks_check WHERE agent_id=(SELECT id FROM agents_agent where agents_agent.hostname = $Agents_HostName) AND check_type='memory')\r\n  ORDER BY x",
          "refId": "A",
          "select": [
            [
              {
                "params": [
                  "boot_time"
                ],
                "type": "column"
              }
            ]
          ],
          "table": "agents_agent",
          "timeColumn": "last_seen",
          "timeColumnType": "timestamp",
          "where": [
            {
              "name": "$__timeFilter",
              "params": [],
              "type": "macro"
            }
          ]
        }
      ],
      "title": "Memory Usage",
      "type": "timeseries"
    },
    {
      "datasource": {
        "type": "postgres",
        "uid": "${Tactical}"
      },
      "description": "Track disk consumption for the selected agent.",
      "fieldConfig": {
        "defaults": {
          "color": {
            "mode": "palette-classic"
          },
          "custom": {
            "axisLabel": "",
            "axisPlacement": "auto",
            "barAlignment": 0,
            "drawStyle": "line",
            "fillOpacity": 0,
            "gradientMode": "hue",
            "hideFrom": {
              "legend": false,
              "tooltip": false,
              "viz": false
            },
            "lineInterpolation": "smooth",
            "lineStyle": {
              "fill": "solid"
            },
            "lineWidth": 1,
            "pointSize": 5,
            "scaleDistribution": {
              "type": "linear"
            },
            "showPoints": "auto",
            "spanNulls": false,
            "stacking": {
              "group": "A",
              "mode": "none"
            },
            "thresholdsStyle": {
              "mode": "line+area"
            }
          },
          "mappings": [],
          "thresholds": {
            "mode": "percentage",
            "steps": [
              {
                "color": "green",
                "value": null
              },
              {
                "color": "dark-red",
                "value": 0.5
              },
              {
                "color": "dark-orange",
                "value": 10
              },
              {
                "color": "green",
                "value": 11
              }
            ]
          }
        },
        "overrides": []
      },
      "gridPos": {
        "h": 11,
        "w": 6,
        "x": 18,
        "y": 2
      },
      "id": 30,
      "options": {
        "legend": {
          "calcs": [],
          "displayMode": "hidden",
          "placement": "bottom"
        },
        "tooltip": {
          "mode": "multi",
          "sort": "none"
        }
      },
      "pluginVersion": "8.0.3",
      "targets": [
        {
          "datasource": {
            "type": "postgres",
            "uid": "${Tactical}"
          },
          "format": "time_series",
          "group": [],
          "metricColumn": "none",
          "rawQuery": true,
          "rawSql": "SELECT \r\n  x AS \"time\",\r\n  y as \"Disk Usage\"\r\nFROM \r\n  checks_checkhistory\r\nWHERE \r\n   x BETWEEN $__timeFrom() AND $__timeTo() \r\n  AND check_id IN (SELECT id FROM checks_check WHERE agent_id=(SELECT id FROM agents_agent where agents_agent.hostname = $Agents_HostName) AND check_type='diskspace')\r\n  ORDER BY x",
          "refId": "A",
          "select": [
            [
              {
                "params": [
                  "boot_time"
                ],
                "type": "column"
              }
            ]
          ],
          "table": "agents_agent",
          "timeColumn": "last_seen",
          "timeColumnType": "timestamp",
          "where": [
            {
              "name": "$__timeFilter",
              "params": [],
              "type": "macro"
            }
          ]
        }
      ],
      "title": "Drive Usage",
      "type": "timeseries"
    },
    {
      "datasource": {
        "type": "postgres",
        "uid": "${Tactical}"
      },
      "description": "Type of CPU installed",
      "fieldConfig": {
        "defaults": {
          "color": {
            "mode": "thresholds"
          },
          "mappings": [],
          "thresholds": {
            "mode": "absolute",
            "steps": [
              {
                "color": "text",
                "value": null
              }
            ]
          }
        },
        "overrides": []
      },
      "gridPos": {
        "h": 2,
        "w": 5,
        "x": 0,
        "y": 4
      },
      "id": 50,
      "options": {
        "colorMode": "value",
        "graphMode": "area",
        "justifyMode": "auto",
        "orientation": "auto",
        "reduceOptions": {
          "calcs": [],
          "fields": "/^concat$/",
          "values": true
        },
        "text": {},
        "textMode": "auto"
      },
      "pluginVersion": "8.4.5",
      "targets": [
        {
          "datasource": {
            "type": "postgres",
            "uid": "${Tactical}"
          },
          "format": "table",
          "group": [],
          "metricColumn": "none",
          "rawQuery": true,
          "rawSql": "select  \r\n  concat(wmi_detail->'cpu'->0->0->>'Name',' \\ ',wmi_detail->'base_board'->0->0->>'Manufacturer')\r\nfrom \r\n  agents_agent\r\nwhere \r\n   agents_agent.hostname = $Agents_HostName",
          "refId": "A",
          "select": [
            [
              {
                "params": [
                  "boot_time"
                ],
                "type": "column"
              }
            ]
          ],
          "table": "agents_agent",
          "timeColumn": "last_seen",
          "timeColumnType": "timestamp",
          "where": [
            {
              "name": "$__timeFilter",
              "params": [],
              "type": "macro"
            }
          ]
        }
      ],
      "title": "CPU Name",
      "type": "stat"
    },
    {
      "datasource": {
        "type": "postgres",
        "uid": "${Tactical}"
      },
      "description": "Agent bone type",
      "fieldConfig": {
        "defaults": {
          "color": {
            "mode": "thresholds"
          },
          "mappings": [],
          "thresholds": {
            "mode": "absolute",
            "steps": [
              {
                "color": "text",
                "value": null
              }
            ]
          }
        },
        "overrides": []
      },
      "gridPos": {
        "h": 2,
        "w": 3,
        "x": 0,
        "y": 6
      },
      "id": 44,
      "options": {
        "colorMode": "value",
        "graphMode": "none",
        "justifyMode": "center",
        "orientation": "auto",
        "reduceOptions": {
          "calcs": [
            "lastNotNull"
          ],
          "fields": "/^concat$/",
          "values": true
        },
        "text": {},
        "textMode": "value"
      },
      "pluginVersion": "8.4.5",
      "targets": [
        {
          "datasource": {
            "type": "postgres",
            "uid": "${Tactical}"
          },
          "format": "table",
          "group": [],
          "metricColumn": "none",
          "rawQuery": true,
          "rawSql": "select   \r\n  concat(SUBSTRING(agents_agent.operating_system,'(.*),'),' ', wmi_detail->'cpu'->0->0->>'DataWidth',' Bit') \r\n  \r\nfrom \r\n  agents_agent\r\nwhere \r\n     agents_agent.hostname = $Agents_HostName\r\n",
          "refId": "A",
          "select": [
            [
              {
                "params": [
                  "boot_time"
                ],
                "type": "column"
              }
            ]
          ],
          "table": "agents_agent",
          "timeColumn": "last_seen",
          "timeColumnType": "timestamp",
          "where": [
            {
              "name": "$__timeFilter",
              "params": [],
              "type": "macro"
            }
          ]
        }
      ],
      "type": "stat"
    },
    {
      "datasource": {
        "type": "postgres",
        "uid": "${Tactical}"
      },
      "fieldConfig": {
        "defaults": {
          "color": {
            "mode": "thresholds"
          },
          "mappings": [
            {
              "options": {
                "Windows not up to date": {
                  "color": "dark-red",
                  "index": 0
                },
                "Windows up to date": {
                  "color": "dark-green",
                  "index": 1
                }
              },
              "type": "value"
            }
          ],
          "thresholds": {
            "mode": "absolute",
            "steps": [
              {
                "color": "green",
                "value": null
              },
              {
                "color": "red",
                "value": 80
              }
            ]
          }
        },
        "overrides": []
      },
      "gridPos": {
        "h": 1,
        "w": 2,
        "x": 3,
        "y": 6
      },
      "id": 59,
      "options": {
        "colorMode": "background",
        "graphMode": "area",
        "justifyMode": "auto",
        "orientation": "auto",
        "reduceOptions": {
          "calcs": [],
          "fields": "/.*/",
          "values": true
        },
        "text": {},
        "textMode": "value"
      },
      "pluginVersion": "8.4.5",
      "targets": [
        {
          "datasource": {
            "type": "postgres",
            "uid": "${Tactical}"
          },
          "format": "table",
          "group": [],
          "metricColumn": "none",
          "rawQuery": true,
          "rawSql": "SELECT\n  CASE\n   WHEN (has_patches_pending = true) THEN 'Windows not up to date'\n    WHEN (has_patches_pending = false) THEN 'Windows up to date'\n  ELSE 'nothing'\n END AS  Statut\nFROM \n  agents_agent\nwhere\n     agents_agent.hostname = $Agents_HostName",
          "refId": "A",
          "select": [
            [
              {
                "params": [
                  "boot_time"
                ],
                "type": "column"
              }
            ]
          ],
          "table": "agents_agent",
          "timeColumn": "last_seen",
          "timeColumnType": "timestamp",
          "where": [
            {
              "name": "$__timeFilter",
              "params": [],
              "type": "macro"
            }
          ]
        }
      ],
      "type": "stat"
    },
    {
      "datasource": {
        "type": "postgres",
        "uid": "${Tactical}"
      },
      "fieldConfig": {
        "defaults": {
          "color": {
            "mode": "thresholds"
          },
          "mappings": [
            {
              "options": {
                "No reboot required": {
                  "color": "dark-green",
                  "index": 1
                },
                "Reboot required": {
                  "color": "dark-red",
                  "index": 0
                }
              },
              "type": "value"
            }
          ],
          "thresholds": {
            "mode": "absolute",
            "steps": [
              {
                "color": "green",
                "value": null
              },
              {
                "color": "red",
                "value": 80
              }
            ]
          }
        },
        "overrides": []
      },
      "gridPos": {
        "h": 1,
        "w": 2,
        "x": 3,
        "y": 7
      },
      "id": 61,
      "options": {
        "colorMode": "background",
        "graphMode": "area",
        "justifyMode": "auto",
        "orientation": "auto",
        "reduceOptions": {
          "calcs": [],
          "fields": "/^statut$/",
          "values": true
        },
        "text": {},
        "textMode": "value"
      },
      "pluginVersion": "8.4.5",
      "targets": [
        {
          "datasource": {
            "type": "postgres",
            "uid": "${Tactical}"
          },
          "format": "table",
          "group": [],
          "metricColumn": "none",
          "rawQuery": true,
          "rawSql": "select\n  CASE\n   WHEN (agents_agent.needs_reboot = true) THEN 'Reboot required'\n    WHEN (agents_agent.needs_reboot = false) THEN 'No reboot required'\n  ELSE 'nothing'\n END AS  Statut\nFrom \n  agents_agent\nWhere\n  agents_agent.hostname = $Agents_HostName\n",
          "refId": "A",
          "select": [
            [
              {
                "params": [
                  "boot_time"
                ],
                "type": "column"
              }
            ]
          ],
          "table": "agents_agent",
          "timeColumn": "last_seen",
          "timeColumnType": "timestamp",
          "where": [
            {
              "name": "$__timeFilter",
              "params": [],
              "type": "macro"
            }
          ]
        }
      ],
      "type": "stat"
    },
    {
      "datasource": {
        "type": "postgres",
        "uid": "${Tactical}"
      },
      "description": "Total Agent Memory",
      "fieldConfig": {
        "defaults": {
          "color": {
            "mode": "thresholds"
          },
          "mappings": [],
          "thresholds": {
            "mode": "absolute",
            "steps": [
              {
                "color": "text",
                "value": null
              }
            ]
          }
        },
        "overrides": []
      },
      "gridPos": {
        "h": 2,
        "w": 2,
        "x": 0,
        "y": 8
      },
      "id": 39,
      "options": {
        "colorMode": "value",
        "graphMode": "none",
        "justifyMode": "center",
        "orientation": "auto",
        "reduceOptions": {
          "calcs": [
            "lastNotNull"
          ],
          "fields": "/.*/",
          "values": true
        },
        "text": {},
        "textMode": "value"
      },
      "pluginVersion": "8.4.5",
      "targets": [
        {
          "datasource": {
            "type": "postgres",
            "uid": "${Tactical}"
          },
          "format": "table",
          "group": [],
          "metricColumn": "none",
          "rawQuery": true,
          "rawSql": "select   \r\n   concat((total_ram),'GB / ',concat(wmi_detail->'mem'->0->0->>'Speed','MHz'))\r\n  \r\nfrom \r\n  agents_agent\r\nwhere \r\n  agents_agent.hostname = $Agents_HostName",
          "refId": "A",
          "select": [
            [
              {
                "params": [
                  "boot_time"
                ],
                "type": "column"
              }
            ]
          ],
          "table": "agents_agent",
          "timeColumn": "last_seen",
          "timeColumnType": "timestamp",
          "where": [
            {
              "name": "$__timeFilter",
              "params": [],
              "type": "macro"
            }
          ]
        }
      ],
      "title": "System Ram",
      "type": "stat"
    },
    {
      "datasource": {
        "type": "postgres",
        "uid": "${Tactical}"
      },
      "description": "Total free disk space",
      "fieldConfig": {
        "defaults": {
          "color": {
            "mode": "thresholds"
          },
          "custom": {
            "align": "auto",
            "displayMode": "auto"
          },
          "mappings": [],
          "thresholds": {
            "mode": "absolute",
            "steps": [
              {
                "color": "text",
                "value": null
              }
            ]
          }
        },
        "overrides": []
      },
      "gridPos": {
        "h": 5,
        "w": 3,
        "x": 2,
        "y": 8
      },
      "id": 43,
      "options": {
        "footer": {
          "fields": "",
          "reducer": [
            "sum"
          ],
          "show": false
        },
        "showHeader": false
      },
      "pluginVersion": "8.4.5",
      "targets": [
        {
          "datasource": {
            "type": "postgres",
            "uid": "${Tactical}"
          },
          "format": "table",
          "group": [],
          "metricColumn": "none",
          "rawQuery": true,
          "rawSql": "select \r\n  concat(items.device,'\\ ', items.free,' free on ',items.total)\r\nfrom \r\n  agents_agent,\r\n  jsonb_to_recordset(disks) as items(device text, free text, total text)\r\nWhere\r\n  agents_agent.hostname = $Agents_HostName",
          "refId": "A",
          "select": [
            [
              {
                "params": [
                  "boot_time"
                ],
                "type": "column"
              }
            ]
          ],
          "table": "agents_agent",
          "timeColumn": "last_seen",
          "timeColumnType": "timestamp",
          "where": [
            {
              "name": "$__timeFilter",
              "params": [],
              "type": "macro"
            }
          ]
        }
      ],
      "title": "Available Disk Space",
      "type": "table"
    },
    {
      "datasource": {
        "type": "postgres",
        "uid": "${Tactical}"
      },
      "description": "",
      "fieldConfig": {
        "defaults": {
          "color": {
            "mode": "thresholds"
          },
          "mappings": [],
          "thresholds": {
            "mode": "percentage",
            "steps": [
              {
                "color": "dark-green",
                "value": null
              },
              {
                "color": "#EAB839",
                "value": 70
              },
              {
                "color": "dark-red",
                "value": 85
              }
            ]
          },
          "unit": "percent"
        },
        "overrides": []
      },
      "gridPos": {
        "h": 3,
        "w": 2,
        "x": 0,
        "y": 10
      },
      "id": 45,
      "options": {
        "orientation": "auto",
        "reduceOptions": {
          "calcs": [],
          "fields": "/^Occupation$/",
          "values": false
        },
        "showThresholdLabels": true,
        "showThresholdMarkers": true,
        "text": {}
      },
      "pluginVersion": "8.4.5",
      "targets": [
        {
          "datasource": {
            "type": "postgres",
            "uid": "${Tactical}"
          },
          "format": "table",
          "group": [],
          "metricColumn": "none",
          "rawQuery": true,
          "rawSql": "select\r\n  disks->0->>'percent' as \"Occupation\"\r\nfrom \r\n  agents_agent\r\nwhere \r\n  agents_agent.hostname = $Agents_HostName\r\n",
          "refId": "A",
          "select": [
            [
              {
                "params": [
                  "boot_time"
                ],
                "type": "column"
              }
            ]
          ],
          "table": "agents_agent",
          "timeColumn": "last_seen",
          "timeColumnType": "timestamp",
          "where": [
            {
              "name": "$__timeFilter",
              "params": [],
              "type": "macro"
            }
          ]
        }
      ],
      "type": "gauge"
    },
    {
      "collapsed": false,
      "gridPos": {
        "h": 1,
        "w": 24,
        "x": 0,
        "y": 13
      },
      "id": 47,
      "panels": [],
      "title": "Information on Client or selected site",
      "type": "row"
    },
    {
      "datasource": {
        "type": "postgres",
        "uid": "${Tactical}"
      },
      "description": "Number of clients connected to TRMM",
      "fieldConfig": {
        "defaults": {
          "color": {
            "mode": "thresholds"
          },
          "mappings": [],
          "thresholds": {
            "mode": "absolute",
            "steps": [
              {
                "color": "green",
                "value": null
              }
            ]
          }
        },
        "overrides": []
      },
      "gridPos": {
        "h": 3,
        "w": 2,
        "x": 0,
        "y": 14
      },
      "id": 31,
      "options": {
        "colorMode": "none",
        "graphMode": "none",
        "justifyMode": "center",
        "orientation": "auto",
        "reduceOptions": {
          "calcs": [
            "lastNotNull"
          ],
          "fields": "",
          "values": false
        },
        "text": {},
        "textMode": "auto"
      },
      "pluginVersion": "8.4.5",
      "targets": [
        {
          "datasource": {
            "type": "postgres",
            "uid": "${Tactical}"
          },
          "format": "table",
          "group": [],
          "metricColumn": "none",
          "rawQuery": true,
          "rawSql": "SELECT\n  count(*)\nFROM agents_agent\nwhere \n  site_id IN (SELECT id FROM clients_site WHERE site_id IN (SELECT id FROM clients_site WHERE name IN ($Sites))) and\n  site_id IN (SELECT id FROM clients_site WHERE client_id IN (SELECT id FROM clients_client WHERE name IN ($Client)))\nORDER BY 1",
          "refId": "A",
          "select": [
            [
              {
                "params": [
                  "boot_time"
                ],
                "type": "column"
              }
            ]
          ],
          "table": "agents_agent",
          "timeColumn": "last_seen",
          "timeColumnType": "timestamp",
          "where": [
            {
              "name": "$__timeFilter",
              "params": [],
              "type": "macro"
            }
          ]
        }
      ],
      "title": "Clients",
      "type": "stat"
    },
    {
      "datasource": {
        "type": "postgres",
        "uid": "${Tactical}"
      },
      "fieldConfig": {
        "defaults": {
          "color": {
            "mode": "thresholds"
          },
          "mappings": [],
          "thresholds": {
            "mode": "absolute",
            "steps": [
              {
                "color": "dark-blue",
                "value": null
              }
            ]
          }
        },
        "overrides": []
      },
      "gridPos": {
        "h": 3,
        "w": 6,
        "x": 2,
        "y": 14
      },
      "id": 24,
      "options": {
        "colorMode": "background",
        "graphMode": "none",
        "justifyMode": "auto",
        "orientation": "auto",
        "reduceOptions": {
          "calcs": [
            "lastNotNull"
          ],
          "fields": "",
          "values": false
        },
        "text": {},
        "textMode": "auto"
      },
      "pluginVersion": "8.4.5",
      "targets": [
        {
          "datasource": {
            "type": "postgres",
            "uid": "${Tactical}"
          },
          "format": "table",
          "group": [],
          "metricColumn": "none",
          "rawQuery": true,
          "rawSql": "SELECT\r\n  count(*)\r\n  FROM alerts_alert\r\nWhere\r\n alerts_alert.severity = 'info' \r\n AND alerts_alert.resolved = false",
          "refId": "A",
          "select": [
            [
              {
                "params": [
                  "boot_time"
                ],
                "type": "column"
              }
            ]
          ],
          "table": "agents_agent",
          "timeColumn": "last_seen",
          "timeColumnType": "timestamp",
          "where": [
            {
              "name": "$__timeFilter",
              "params": [],
              "type": "macro"
            }
          ]
        }
      ],
      "title": "Information Alerts",
      "type": "stat"
    },
    {
      "datasource": {
        "type": "postgres",
        "uid": "${Tactical}"
      },
      "fieldConfig": {
        "defaults": {
          "color": {
            "mode": "thresholds"
          },
          "mappings": [],
          "thresholds": {
            "mode": "absolute",
            "steps": [
              {
                "color": "dark-blue",
                "value": null
              },
              {
                "color": "#EAB839",
                "value": 0
              }
            ]
          }
        },
        "overrides": []
      },
      "gridPos": {
        "h": 3,
        "w": 8,
        "x": 8,
        "y": 14
      },
      "id": 20,
      "options": {
        "colorMode": "background",
        "graphMode": "none",
        "justifyMode": "auto",
        "orientation": "auto",
        "reduceOptions": {
          "calcs": [
            "lastNotNull"
          ],
          "fields": "",
          "values": false
        },
        "text": {},
        "textMode": "auto"
      },
      "pluginVersion": "8.4.5",
      "targets": [
        {
          "datasource": {
            "type": "postgres",
            "uid": "${Tactical}"
          },
          "format": "table",
          "group": [],
          "metricColumn": "none",
          "rawQuery": true,
          "rawSql": "SELECT\r\n  count(*)\r\n  FROM alerts_alert\r\nWhere\r\n alerts_alert.severity = 'warning' \r\n AND alerts_alert.resolved = false",
          "refId": "A",
          "select": [
            [
              {
                "params": [
                  "boot_time"
                ],
                "type": "column"
              }
            ]
          ],
          "table": "agents_agent",
          "timeColumn": "last_seen",
          "timeColumnType": "timestamp",
          "where": [
            {
              "name": "$__timeFilter",
              "params": [],
              "type": "macro"
            }
          ]
        }
      ],
      "title": "Warning Alerts",
      "type": "stat"
    },
    {
      "datasource": {
        "type": "postgres",
        "uid": "${Tactical}"
      },
      "description": "",
      "fieldConfig": {
        "defaults": {
          "color": {
            "mode": "thresholds"
          },
          "mappings": [],
          "thresholds": {
            "mode": "absolute",
            "steps": [
              {
                "color": "green",
                "value": null
              },
              {
                "color": "red",
                "value": 0
              }
            ]
          }
        },
        "overrides": []
      },
      "gridPos": {
        "h": 3,
        "w": 8,
        "x": 16,
        "y": 14
      },
      "id": 23,
      "options": {
        "colorMode": "background",
        "graphMode": "none",
        "justifyMode": "auto",
        "orientation": "auto",
        "reduceOptions": {
          "calcs": [
            "lastNotNull"
          ],
          "fields": "",
          "values": false
        },
        "text": {},
        "textMode": "auto"
      },
      "pluginVersion": "8.4.5",
      "targets": [
        {
          "datasource": {
            "type": "postgres",
            "uid": "${Tactical}"
          },
          "format": "table",
          "group": [],
          "metricColumn": "none",
          "rawQuery": true,
          "rawSql": "SELECT\r\n  count(*) as \"error\"\r\n  FROM alerts_alert\r\nWhere\r\n alerts_alert.severity = 'error'  \r\n AND alerts_alert.resolved = false",
          "refId": "A",
          "select": [
            [
              {
                "params": [
                  "boot_time"
                ],
                "type": "column"
              }
            ]
          ],
          "table": "agents_agent",
          "timeColumn": "last_seen",
          "timeColumnType": "timestamp",
          "where": [
            {
              "name": "$__timeFilter",
              "params": [],
              "type": "macro"
            }
          ]
        }
      ],
      "title": "Error Alerts",
      "type": "stat"
    },
    {
      "datasource": {
        "type": "postgres",
        "uid": "${Tactical}"
      },
      "fieldConfig": {
        "defaults": {
          "color": {
            "mode": "palette-classic"
          },
          "custom": {
            "hideFrom": {
              "legend": false,
              "tooltip": false,
              "viz": false
            }
          },
          "mappings": [],
          "unit": "percent"
        },
        "overrides": []
      },
      "gridPos": {
        "h": 8,
        "w": 5,
        "x": 0,
        "y": 17
      },
      "id": 18,
      "options": {
        "displayLabels": [
          "percent",
          "name"
        ],
        "legend": {
          "displayMode": "hidden",
          "placement": "right",
          "values": [
            "percent"
          ]
        },
        "pieType": "pie",
        "reduceOptions": {
          "calcs": [
            "lastNotNull"
          ],
          "fields": "",
          "values": false
        },
        "tooltip": {
          "mode": "single",
          "sort": "none"
        }
      },
      "pluginVersion": "8.0.3",
      "targets": [
        {
          "datasource": {
            "type": "postgres",
            "uid": "${Tactical}"
          },
          "format": "table",
          "group": [],
          "metricColumn": "none",
          "rawQuery": true,
          "rawSql": "  select (\r\nSELECT\r\n  count(*)\r\n  FROM agents_agent\r\nWhere\r\n  SUBSTRING(agents_agent.operating_system,POSITION(',' in agents_agent.operating_system)+2,2) = '64' and\r\n  site_id IN (SELECT id FROM clients_site WHERE site_id IN (SELECT id FROM clients_site WHERE name IN ($Sites))) and\r\n  site_id IN (SELECT id FROM clients_site WHERE client_id IN (SELECT id FROM clients_client WHERE name IN ($Client)))) as \"64 Bit\",\r\n\r\n  (SELECT\r\n  count(*)\r\n  FROM agents_agent\r\nWhere\r\n  SUBSTRING(agents_agent.operating_system,POSITION(',' in agents_agent.operating_system)+2,2) = '32' and\r\n   site_id IN (SELECT id FROM clients_site WHERE site_id IN (SELECT id FROM clients_site WHERE name IN ($Sites))) and\r\n  site_id IN (SELECT id FROM clients_site WHERE client_id IN (SELECT id FROM clients_client WHERE name IN ($Client)))) as \"32 Bit\" ",
          "refId": "A",
          "select": [
            [
              {
                "params": [
                  "boot_time"
                ],
                "type": "column"
              }
            ]
          ],
          "table": "agents_agent",
          "timeColumn": "last_seen",
          "timeColumnType": "timestamp",
          "where": [
            {
              "name": "$__timeFilter",
              "params": [],
              "type": "macro"
            }
          ]
        }
      ],
      "title": "OS Distribution",
      "type": "piechart"
    },
    {
      "datasource": {
        "type": "postgres",
        "uid": "${Tactical}"
      },
      "description": "List all OS installed",
      "fieldConfig": {
        "defaults": {
          "color": {
            "fixedColor": "semi-dark-green",
            "mode": "fixed"
          },
          "mappings": [],
          "thresholds": {
            "mode": "absolute",
            "steps": [
              {
                "color": "green",
                "value": null
              }
            ]
          }
        },
        "overrides": []
      },
      "gridPos": {
        "h": 17,
        "w": 6,
        "x": 5,
        "y": 17
      },
      "id": 26,
      "options": {
        "displayMode": "basic",
        "orientation": "horizontal",
        "reduceOptions": {
          "calcs": [
            "last"
          ],
          "fields": "/.*/",
          "values": true
        },
        "showUnfilled": true,
        "text": {}
      },
      "pluginVersion": "8.4.5",
      "targets": [
        {
          "datasource": {
            "type": "postgres",
            "uid": "${Tactical}"
          },
          "format": "table",
          "group": [],
          "metricColumn": "none",
          "rawQuery": true,
          "rawSql": "  SELECT \r\n  count(*) as \"count\",\r\n  SUBSTRING(agents_agent.operating_system,'(.*)bit') AS \"Operating System\"\r\n  FROM agents_agent\r\nINNER JOIN clients_site on site_id = clients_site.id\r\n\r\nWHERE site_id IN (SELECT id FROM clients_site WHERE client_id IN (SELECT id FROM clients_client WHERE name IN ($Client)))\r\nAND site_id IN (SELECT id FROM clients_site WHERE site_id IN (SELECT id FROM clients_site WHERE name IN ($Sites)))\r\nGroup by \"Operating System\"\r\nOrder by \"count\" desc\r\n  ",
          "refId": "A",
          "select": [
            [
              {
                "params": [
                  "boot_time"
                ],
                "type": "column"
              }
            ]
          ],
          "table": "agents_agent",
          "timeColumn": "last_seen",
          "timeColumnType": "timestamp",
          "where": [
            {
              "name": "$__timeFilter",
              "params": [],
              "type": "macro"
            }
          ]
        }
      ],
      "title": "OS Type",
      "transformations": [],
      "type": "bargauge"
    },
    {
      "datasource": {
        "type": "postgres",
        "uid": "${Tactical}"
      },
      "description": "List all installed processors",
      "fieldConfig": {
        "defaults": {
          "color": {
            "fixedColor": "semi-dark-green",
            "mode": "fixed"
          },
          "mappings": [],
          "thresholds": {
            "mode": "absolute",
            "steps": [
              {
                "color": "green",
                "value": null
              }
            ]
          }
        },
        "overrides": []
      },
      "gridPos": {
        "h": 17,
        "w": 7,
        "x": 11,
        "y": 17
      },
      "id": 54,
      "options": {
        "displayMode": "basic",
        "orientation": "horizontal",
        "reduceOptions": {
          "calcs": [
            "last"
          ],
          "fields": "/.*/",
          "values": true
        },
        "showUnfilled": true,
        "text": {}
      },
      "pluginVersion": "8.4.5",
      "targets": [
        {
          "datasource": {
            "type": "postgres",
            "uid": "${Tactical}"
          },
          "format": "table",
          "group": [],
          "metricColumn": "none",
          "rawQuery": true,
          "rawSql": "  SELECT \r\n  count(*) as \"count\",\r\n  wmi_detail->'cpu'->0->0->>'Name' as \"CPU Name\"\r\n  FROM agents_agent\r\nINNER JOIN clients_site on site_id = clients_site.id\r\n\r\nWHERE site_id IN (SELECT id FROM clients_site WHERE client_id IN (SELECT id FROM clients_client WHERE name IN ($Client)))\r\nAND site_id IN (SELECT id FROM clients_site WHERE site_id IN (SELECT id FROM clients_site WHERE name IN ($Sites)))\r\nGroup by \"CPU Name\"\r\nOrder by \"count\" desc\r\n  ",
          "refId": "A",
          "select": [
            [
              {
                "params": [
                  "boot_time"
                ],
                "type": "column"
              }
            ]
          ],
          "table": "agents_agent",
          "timeColumn": "last_seen",
          "timeColumnType": "timestamp",
          "where": [
            {
              "name": "$__timeFilter",
              "params": [],
              "type": "macro"
            }
          ]
        }
      ],
      "title": "Processor type",
      "type": "bargauge"
    },
    {
      "datasource": {
        "type": "postgres",
        "uid": "${Tactical}"
      },
      "description": "List all installed memory",
      "fieldConfig": {
        "defaults": {
          "color": {
            "fixedColor": "semi-dark-green",
            "mode": "fixed"
          },
          "mappings": [],
          "thresholds": {
            "mode": "absolute",
            "steps": [
              {
                "color": "green",
                "value": null
              }
            ]
          }
        },
        "overrides": []
      },
      "gridPos": {
        "h": 17,
        "w": 6,
        "x": 18,
        "y": 17
      },
      "id": 55,
      "options": {
        "displayMode": "basic",
        "orientation": "horizontal",
        "reduceOptions": {
          "calcs": [
            "last"
          ],
          "fields": "/.*/",
          "values": true
        },
        "showUnfilled": true,
        "text": {}
      },
      "pluginVersion": "8.4.5",
      "targets": [
        {
          "datasource": {
            "type": "postgres",
            "uid": "${Tactical}"
          },
          "format": "table",
          "group": [],
          "metricColumn": "none",
          "rawQuery": true,
          "rawSql": "  SELECT \r\n  count(*) as \"count\",\r\n  concat((total_ram),' GB') as \"Size Memory\"\r\n  FROM agents_agent\r\nINNER JOIN clients_site on site_id = clients_site.id\r\n\r\nWHERE\r\n site_id IN (SELECT id FROM clients_site WHERE client_id IN (SELECT id FROM clients_client WHERE name IN ($Client)))\r\nAND site_id IN (SELECT id FROM clients_site WHERE site_id IN (SELECT id FROM clients_site WHERE name IN ($Sites)))\r\nGroup by \"Size Memory\"\r\nOrder by \"Size Memory\" desc\r\n  ",
          "refId": "A",
          "select": [
            [
              {
                "params": [
                  "boot_time"
                ],
                "type": "column"
              }
            ]
          ],
          "table": "agents_agent",
          "timeColumn": "last_seen",
          "timeColumnType": "timestamp",
          "where": [
            {
              "name": "$__timeFilter",
              "params": [],
              "type": "macro"
            }
          ]
        }
      ],
      "title": "Installed System RAM",
      "type": "bargauge"
    },
    {
      "datasource": {
        "type": "postgres",
        "uid": "${Tactical}"
      },
      "description": "Number of clients connected to TRMM",
      "fieldConfig": {
        "defaults": {
          "color": {
            "mode": "thresholds"
          },
          "custom": {
            "align": "auto",
            "displayMode": "auto"
          },
          "mappings": [],
          "thresholds": {
            "mode": "absolute",
            "steps": [
              {
                "color": "green",
                "value": null
              }
            ]
          }
        },
        "overrides": [
          {
            "matcher": {
              "id": "byName",
              "options": "Site"
            },
            "properties": [
              {
                "id": "custom.width",
                "value": 79
              }
            ]
          },
          {
            "matcher": {
              "id": "byName",
              "options": "Last Reboot"
            },
            "properties": [
              {
                "id": "custom.width"
              }
            ]
          }
        ]
      },
      "gridPos": {
        "h": 13,
        "w": 9,
        "x": 0,
        "y": 34
      },
      "id": 14,
      "options": {
        "footer": {
          "fields": "",
          "reducer": [
            "sum"
          ],
          "show": false
        },
        "showHeader": true,
        "sortBy": [
          {
            "desc": false,
            "displayName": "Last Reboot"
          }
        ]
      },
      "pluginVersion": "8.4.5",
      "targets": [
        {
          "datasource": {
            "type": "postgres",
            "uid": "${Tactical}"
          },
          "format": "table",
          "group": [],
          "metricColumn": "none",
          "rawQuery": true,
          "rawSql": "SELECT \r\n  clients_site.name AS \"Site\",\r\n  hostname AS \"Hostname\",\r\n  description as \"Description\",\r\n  last_seen AS \"Last Response\",\r\n  to_timestamp(boot_time) AS \"Last Reboot\"\r\nFROM agents_agent\r\nINNER JOIN clients_site on site_id = clients_site.id\r\n\r\nWHERE \r\nsite_id IN (SELECT id FROM clients_site WHERE client_id IN (SELECT id FROM clients_client WHERE name IN ($Client)))\r\nAND site_id IN (SELECT id FROM clients_site WHERE site_id IN (SELECT id FROM clients_site WHERE name IN ($Sites)))",
          "refId": "A",
          "select": [
            [
              {
                "params": [
                  "boot_time"
                ],
                "type": "column"
              }
            ]
          ],
          "table": "agents_agent",
          "timeColumn": "last_seen",
          "timeColumnType": "timestamp",
          "where": [
            {
              "name": "$__timeFilter",
              "params": [],
              "type": "macro"
            }
          ]
        }
      ],
      "title": "Client last reboot",
      "type": "table"
    },
    {
      "datasource": {
        "type": "postgres",
        "uid": "${Tactical}"
      },
      "fieldConfig": {
        "defaults": {
          "color": {
            "mode": "thresholds"
          },
          "custom": {
            "align": "auto",
            "displayMode": "auto"
          },
          "mappings": [],
          "thresholds": {
            "mode": "absolute",
            "steps": [
              {
                "color": "green",
                "value": null
              },
              {
                "color": "red",
                "value": 80
              }
            ]
          }
        },
        "overrides": [
          {
            "matcher": {
              "id": "byName",
              "options": "Date Message"
            },
            "properties": [
              {
                "id": "custom.width",
                "value": 185
              }
            ]
          },
          {
            "matcher": {
              "id": "byName",
              "options": "severity"
            },
            "properties": [
              {
                "id": "custom.width",
                "value": 117
              }
            ]
          },
          {
            "matcher": {
              "id": "byName",
              "options": "Severity"
            },
            "properties": [
              {
                "id": "custom.width",
                "value": 190
              }
            ]
          }
        ]
      },
      "gridPos": {
        "h": 13,
        "w": 15,
        "x": 9,
        "y": 34
      },
      "id": 33,
      "options": {
        "footer": {
          "fields": "",
          "reducer": [
            "sum"
          ],
          "show": false
        },
        "showHeader": true,
        "sortBy": []
      },
      "pluginVersion": "8.4.5",
      "targets": [
        {
          "datasource": {
            "type": "postgres",
            "uid": "${Tactical}"
          },
          "format": "table",
          "group": [],
          "metricColumn": "none",
          "rawQuery": true,
          "rawSql": "SELECT \r\n  alert_time as \"Date Message\",\r\n  alerts_alert.severity as \"Severity\",\r\n  message as \"Messages\"\r\n  FROM alerts_alert\r\nWHERE \r\n alerts_alert.severity = '$Message_Severity'\r\n AND alerts_alert.resolved = false",
          "refId": "A",
          "select": [
            [
              {
                "params": [
                  "boot_time"
                ],
                "type": "column"
              }
            ]
          ],
          "table": "agents_agent",
          "timeColumn": "last_seen",
          "timeColumnType": "timestamp",
          "where": [
            {
              "name": "$__timeFilter",
              "params": [],
              "type": "macro"
            }
          ]
        }
      ],
      "title": "Error Messages",
      "type": "table"
    }
  ],
  "refresh": "",
  "schemaVersion": 35,
  "style": "dark",
  "tags": [
    "TRMMAgentDashboard"
  ],
  "templating": {
    "list": [
      {
        "current": {
          "selected": false,
          "text": "All",
          "value": "$__all"
        },
        "datasource": {
          "type": "postgres",
          "uid": "${Tactical}"
        },
        "definition": "SELECT name FROM clients_client order by name",
        "hide": 0,
        "includeAll": true,
        "multi": false,
        "name": "Client",
        "options": [],
        "query": "SELECT name FROM clients_client order by name",
        "refresh": 1,
        "regex": "",
        "skipUrlSync": false,
        "sort": 0,
        "tagValuesQuery": "",
        "tagsQuery": "",
        "type": "query",
        "useTags": false
      },
      {
        "current": {
          "selected": false,
          "text": "All",
          "value": "$__all"
        },
        "datasource": {
          "type": "postgres",
          "uid": "${Tactical}"
        },
        "definition": "SELECT name FROM clients_site",
        "hide": 0,
        "includeAll": true,
        "multi": false,
        "name": "Sites",
        "options": [],
        "query": "SELECT name FROM clients_site",
        "refresh": 1,
        "regex": "",
        "skipUrlSync": false,
        "sort": 0,
        "type": "query"
      },
      {
        "current": {
          "selected": false,
          "text": "All",
          "value": "$__all"
        },
        "datasource": {
          "type": "postgres",
          "uid": "${Tactical}"
        },
        "definition": "SELECT \nhostname\nFROM \nagents_agent\n\n",
        "hide": 0,
        "includeAll": true,
        "multi": false,
        "name": "Agents_HostName",
        "options": [],
        "query": "SELECT \nhostname\nFROM \nagents_agent\n\n",
        "refresh": 1,
        "regex": "",
        "skipUrlSync": false,
        "sort": 1,
        "type": "query"
      },
      {
        "current": {
          "isNone": true,
          "selected": false,
          "text": "None",
          "value": ""
        },
        "datasource": {
          "type": "postgres",
          "uid": "${Tactical}"
        },
        "definition": "SELECT \nalerts_alert.severity\n  FROM alerts_alert",
        "hide": 0,
        "includeAll": false,
        "multi": false,
        "name": "Message_Severity",
        "options": [],
        "query": "SELECT \nalerts_alert.severity\n  FROM alerts_alert",
        "refresh": 1,
        "regex": "",
        "skipUrlSync": false,
        "sort": 1,
        "type": "query"
      },
      {
        "current": {
          "selected": false,
          "text": "TacticalRMM",
          "value": "TacticalRMM"
        },
        "hide": 2,
        "includeAll": false,
        "multi": false,
        "name": "Tactical",
        "options": [],
        "query": "postgres",
        "refresh": 1,
        "regex": "TacticalRMM",
        "skipUrlSync": false,
        "type": "datasource"
      }
    ]
  },
  "time": {
    "from": "now-1h",
    "to": "now"
  },
  "timepicker": {
    "hidden": false
  },
  "timezone": "",
  "title": "TacticalRMM Agent dashboard",
  "uid": "pLkA1-inz",
  "version": 6,
  "weekStart": ""
}
